factoradic/__init__.py
factoradic/__main__.py
factoradic/cli.py
factoradic/convert.py
factoradic-1.0.3.dist-info/DESCRIPTION.rst
factoradic-1.0.3.dist-info/METADATA
factoradic-1.0.3.dist-info/RECORD
factoradic-1.0.3.dist-info/WHEEL
factoradic-1.0.3.dist-info/entry_points.txt
factoradic-1.0.3.dist-info/metadata.json
factoradic-1.0.3.dist-info/top_level.txt
