Metadata-Version: 2.0
Name: factoradic
Version: 1.0.3
Summary: Convert integers to and from the factoradic number system
Home-page: https://github.com/rob-smallshire/factoradic
Author: Robert Smallshire
Author-email: rob@sixty-north.com
License: MIT License
Keywords: combinatorics factoradic factorial number-systems permutations
Platform: UNKNOWN
Classifier: Development Status :: 5 - Production/Stable
Classifier: Intended Audience :: Developers
Classifier: Topic :: Scientific/Engineering :: Mathematics
Classifier: Topic :: Software Development :: Libraries
Classifier: License :: OSI Approved :: MIT License
Classifier: Programming Language :: Python :: 3 :: Only
Provides-Extra: dev
Requires-Dist: check-manifest; extra == 'dev'
Requires-Dist: wheel; extra == 'dev'
Provides-Extra: doc
Requires-Dist: sphinx; extra == 'doc'
Requires-Dist: cartouche; extra == 'doc'
Requires-Dist: sphinx-rtd-theme; extra == 'doc'
Provides-Extra: test
Requires-Dist: coverage; extra == 'test'
Requires-Dist: hypothesis; extra == 'test'
Requires-Dist: pytest; extra == 'test'
